intelino/scan/__main__.py
intelino/trainlib_async/__init__.py
intelino/trainlib_async/exc.py
intelino/trainlib_async/helpers.py
intelino/trainlib_async/message_builder.py
intelino/trainlib_async/messages.py
intelino/trainlib_async/train.py
intelino/trainlib_async/train_ble_device.py
intelino/trainlib_async/train_ble_packet.py
intelino/trainlib_async/train_factory.py
intelino/trainlib_async/train_scanner.py
intelino/trainlib_async/drivers/bleak_driver.py
intelino/trainlib_async/drivers/train_ble_driver.py
intelino/trainlib_async/enums/__init__.py
intelino/trainlib_async/enums/enums.py
intelino/trainlib_async/enums/internals.py
intelino_trainlib_async-1.0.4.dist-info/LICENSE
intelino_trainlib_async-1.0.4.dist-info/METADATA
intelino_trainlib_async-1.0.4.dist-info/WHEEL
intelino_trainlib_async-1.0.4.dist-info/top_level.txt
intelino_trainlib_async-1.0.4.dist-info/RECORD
