Metadata-Version: 2.1
Name: intelino-trainlib-async
Version: 1.0.4
Summary: Asynchronous Python library (SDK) for interacting with the intelino smart train.
Home-page: https://intelino.com
Author: intelino
Author-email: developer@intelino.com
License: Intelino Public License
Project-URL: Documentation, https://intelino-trainlib-async-py.readthedocs.io/
Project-URL: Source Code, https://github.com/intelino-code/intelino-trainlib-async-py
Project-URL: Intelino Lab, https://lab.intelino.com
Classifier: Framework :: AsyncIO
Classifier: Intended Audience :: Developers
Classifier: Intended Audience :: Education
Classifier: License :: Other/Proprietary License
Classifier: Operating System :: Microsoft :: Windows :: Windows 10
Classifier: Operating System :: POSIX :: Linux
Classifier: Operating System :: MacOS :: MacOS X
Classifier: Programming Language :: Python
Classifier: Programming Language :: Python :: 3
Classifier: Programming Language :: Python :: 3.7
Classifier: Programming Language :: Python :: 3.8
Classifier: Programming Language :: Python :: 3.9
Classifier: Programming Language :: Python :: 3 :: Only
Classifier: Typing :: Typed
Requires-Python: >=3.7
License-File: LICENSE
Requires-Dist: bleak
Requires-Dist: Rx
Requires-Dist: typing-extensions
